dfault/objects.py
dfault-1.0.5.dist-info/DESCRIPTION.rst
dfault-1.0.5.dist-info/METADATA
dfault-1.0.5.dist-info/RECORD
dfault-1.0.5.dist-info/WHEEL
dfault-1.0.5.dist-info/metadata.json
dfault-1.0.5.dist-info/top_level.txt
