Metadata-Version: 2.0
Name: dfault
Version: 1.0.5
Summary: A simple lightweight class that allows the user to fallback on default values
Home-page: http://www.joeyism.com
Author: Joey Sham
Author-email: sham.joey@gmail.com
License: UNKNOWN
Platform: UNKNOWN
